ChangeLog
LICENSE.txt
MANIFEST.in
README.txt
TODO.txt
licenses.txt
make3.py
setup.cfg
setup.py
setup2.py
setup3.py
test-full_prerelease.py
test.py
test2.py
test3.py
Lib3/bsddb/__init__.py
Lib3/bsddb/db.py
Lib3/bsddb/dbobj.py
Lib3/bsddb/dbrecio.py
Lib3/bsddb/dbshelve.py
Lib3/bsddb/dbtables.py
Lib3/bsddb/dbutils.py
Lib3/bsddb/test/__init__.py
Lib3/bsddb/test/test_all.py
Lib3/bsddb/test/test_associate.py
Lib3/bsddb/test/test_basics.py
Lib3/bsddb/test/test_compare.py
Lib3/bsddb/test/test_compat.py
Lib3/bsddb/test/test_cursor_pget_bug.py
Lib3/bsddb/test/test_db.py
Lib3/bsddb/test/test_dbenv.py
Lib3/bsddb/test/test_dbobj.py
Lib3/bsddb/test/test_dbshelve.py
Lib3/bsddb/test/test_dbtables.py
Lib3/bsddb/test/test_distributed_transactions.py
Lib3/bsddb/test/test_early_close.py
Lib3/bsddb/test/test_fileid.py
Lib3/bsddb/test/test_get_none.py
Lib3/bsddb/test/test_join.py
Lib3/bsddb/test/test_lock.py
Lib3/bsddb/test/test_misc.py
Lib3/bsddb/test/test_pickle.py
Lib3/bsddb/test/test_queue.py
Lib3/bsddb/test/test_recno.py
Lib3/bsddb/test/test_replication.py
Lib3/bsddb/test/test_sequence.py
Lib3/bsddb/test/test_thread.py
Modules/_bsddb.c
Modules/bsddb.h
bsddb3.egg-info/PKG-INFO
bsddb3.egg-info/SOURCES.txt
bsddb3.egg-info/dependency_links.txt
bsddb3.egg-info/top_level.txt
docs/README.txt
docs/bitcoin.png
docs/contents.rst
docs/db.rst
docs/dbcursor.rst
docs/dbenv.rst
docs/dblock.rst
docs/dblogcursor.rst
docs/dbsequence.rst
docs/dbsite.rst
docs/dbtxn.rst
docs/donate.rst
docs/history.rst
docs/introduction.rst
docs/license.rst
docs/html/db.html
docs/html/dbcursor.html
docs/html/dbenv.html
docs/html/dblock.html
docs/html/dblogcursor.html
docs/html/dbsequence.html
docs/html/dbsite.html
docs/html/dbtxn.html
docs/html/donate.html
docs/html/genindex.html
docs/html/history.html
docs/html/index.html
docs/html/introduction.html
docs/html/license.html
docs/html/search.html
docs/html/searchindex.js
docs/html/images/bitcoin.png
docs/html/static/alabaster.css
docs/html/static/basic.css
docs/html/static/custom.css
docs/html/static/doctools.js
docs/html/static/documentation_options.js
docs/html/static/file.png
