Metadata-Version: 2.1
Name: bsddb3
Version: 6.2.8
Summary: Python bindings for Oracle Berkeley DB
Home-page: https://www.jcea.es/programacion/pybsddb.htm
Author: Jesus Cea, Robin Dunn, Gregory P. Smith, Andrew Kuchling, Barry Warsaw
Author-email: pybsddb@jcea.es
License: 3-clause BSD License
Platform: UNKNOWN
Classifier: License :: OSI Approved :: BSD License
Classifier: Development Status :: 5 - Production/Stable
Classifier: Intended Audience :: Developers
Classifier: Intended Audience :: Information Technology
Classifier: Natural Language :: English
Classifier: Natural Language :: Spanish
Classifier: Operating System :: OS Independent
Classifier: Programming Language :: Python
Classifier: Topic :: Database
Classifier: Topic :: Software Development
Classifier: Topic :: System :: Clustering
Classifier: Programming Language :: Python :: 2
Classifier: Programming Language :: Python :: 2.6
Classifier: Programming Language :: Python :: 2.7
Classifier: Programming Language :: Python :: 3
Classifier: Programming Language :: Python :: 3.3
Classifier: Programming Language :: Python :: 3.4
Classifier: Programming Language :: Python :: 3.5
Classifier: Programming Language :: Python :: 3.6
Classifier: Programming Language :: Python :: 3.7
Classifier: Programming Language :: Python :: 3.8
Classifier: Programming Language :: Python :: 3.9
